flaskscaffold/__init__.py
flaskscaffold/flaskscaffold.py
flaskscaffold/complimentary_files/.gitignore
flaskscaffold/complimentary_files/app.py
flaskscaffold-0.9.dist-info/DESCRIPTION.rst
flaskscaffold-0.9.dist-info/METADATA
flaskscaffold-0.9.dist-info/RECORD
flaskscaffold-0.9.dist-info/WHEEL
flaskscaffold-0.9.dist-info/entry_points.txt
flaskscaffold-0.9.dist-info/metadata.json
flaskscaffold-0.9.dist-info/top_level.txt
