Metadata-Version: 2.0
Name: flaskscaffold
Version: 0.9
Summary: Initializing project structure for flask applications.
Home-page: https://github.com/karolosk/flask-scaffold
Author: KarolosK
Author-email: karolos.koutsoulelos@gmail.com
License: MIT
Platform: UNKNOWN
Requires-Dist: click
